{
  "_generated": "2026-04-01T15:15:13",
  "_source": "11150大渡河智能体.json",
  "_description": "各水库水位-面积关系 A(H)（从实测断面沿程积分）",
  "s3": {
    "name": "枕头坝",
    "channel": "sxg-ztb",
    "n_sections": 15,
    "curve": [
      {
        "H": 620.0,
        "A_m2": 2157626.81
      },
      {
        "H": 620.241,
        "A_m2": 2178761.63
      },
      {
        "H": 620.483,
        "A_m2": 2184738.05
      },
      {
        "H": 620.724,
        "A_m2": 2188627.57
      },
      {
        "H": 620.966,
        "A_m2": 2205530.76
      },
      {
        "H": 621.207,
        "A_m2": 2209268.05
      },
      {
        "H": 621.448,
        "A_m2": 2213916.48
      },
      {
        "H": 621.69,
        "A_m2": 2220675.35
      },
      {
        "H": 621.931,
        "A_m2": 2223060.69
      },
      {
        "H": 622.172,
        "A_m2": 2229418.45
      },
      {
        "H": 622.414,
        "A_m2": 2229418.45
      },
      {
        "H": 622.655,
        "A_m2": 2241782.92
      },
      {
        "H": 622.897,
        "A_m2": 2243258.14
      },
      {
        "H": 623.138,
        "A_m2": 2243258.14
      },
      {
        "H": 623.379,
        "A_m2": 2243258.14
      },
      {
        "H": 623.621,
        "A_m2": 2243258.14
      },
      {
        "H": 623.862,
        "A_m2": 2244447.38
      },
      {
        "H": 624.103,
        "A_m2": 2244447.38
      },
      {
        "H": 624.345,
        "A_m2": 2244447.38
      },
      {
        "H": 624.586,
        "A_m2": 2244447.38
      },
      {
        "H": 624.828,
        "A_m2": 2249399.05
      },
      {
        "H": 625.069,
        "A_m2": 2252200.36
      },
      {
        "H": 625.31,
        "A_m2": 2262485.86
      },
      {
        "H": 625.552,
        "A_m2": 2262485.86
      },
      {
        "H": 625.793,
        "A_m2": 2262485.86
      },
      {
        "H": 626.034,
        "A_m2": 2262485.86
      },
      {
        "H": 626.276,
        "A_m2": 2262485.86
      },
      {
        "H": 626.517,
        "A_m2": 2301102.01
      },
      {
        "H": 626.759,
        "A_m2": 2312197.3
      },
      {
        "H": 627.0,
        "A_m2": 2326382.94
      }
    ]
  },
  "s2": {
    "name": "深溪沟",
    "channel": "pbg-sxg",
    "n_sections": 18,
    "curve": [
      {
        "H": 655.0,
        "A_m2": 1490362.88
      },
      {
        "H": 655.241,
        "A_m2": 1490500.49
      },
      {
        "H": 655.483,
        "A_m2": 1492559.46
      },
      {
        "H": 655.724,
        "A_m2": 1511750.2
      },
      {
        "H": 655.966,
        "A_m2": 1518961.82
      },
      {
        "H": 656.207,
        "A_m2": 1524826.26
      },
      {
        "H": 656.448,
        "A_m2": 1524826.26
      },
      {
        "H": 656.69,
        "A_m2": 1536168.28
      },
      {
        "H": 656.931,
        "A_m2": 1550495.22
      },
      {
        "H": 657.172,
        "A_m2": 1550495.22
      },
      {
        "H": 657.414,
        "A_m2": 1560053.77
      },
      {
        "H": 657.655,
        "A_m2": 1560053.77
      },
      {
        "H": 657.897,
        "A_m2": 1568263.98
      },
      {
        "H": 658.138,
        "A_m2": 1581445.84
      },
      {
        "H": 658.379,
        "A_m2": 1673549.45
      },
      {
        "H": 658.621,
        "A_m2": 1673549.45
      },
      {
        "H": 658.862,
        "A_m2": 1673549.45
      },
      {
        "H": 659.103,
        "A_m2": 1701363.6
      },
      {
        "H": 659.345,
        "A_m2": 1701363.6
      },
      {
        "H": 659.586,
        "A_m2": 1701363.6
      },
      {
        "H": 659.828,
        "A_m2": 1708121.33
      },
      {
        "H": 660.069,
        "A_m2": 1734318.77
      },
      {
        "H": 660.31,
        "A_m2": 1749437.92
      },
      {
        "H": 660.552,
        "A_m2": 1757297.74
      },
      {
        "H": 660.793,
        "A_m2": 1776184.81
      },
      {
        "H": 661.034,
        "A_m2": 1794790.7
      },
      {
        "H": 661.276,
        "A_m2": 1820641.0
      },
      {
        "H": 661.517,
        "A_m2": 1833625.54
      },
      {
        "H": 661.759,
        "A_m2": 1833625.54
      },
      {
        "H": 662.0,
        "A_m2": 1833625.54
      }
    ]
  },
  "s1": {
    "name": "瀑布沟",
    "channel": "sm-pbg",
    "n_sections": 50,
    "curve": [
      {
        "H": 790.0,
        "A_m2": 34257703.09
      },
      {
        "H": 792.138,
        "A_m2": 37538589.12
      },
      {
        "H": 794.276,
        "A_m2": 38504664.39
      },
      {
        "H": 796.414,
        "A_m2": 40324883.54
      },
      {
        "H": 798.552,
        "A_m2": 42524431.76
      },
      {
        "H": 800.69,
        "A_m2": 43888955.41
      },
      {
        "H": 802.828,
        "A_m2": 45225556.83
      },
      {
        "H": 804.966,
        "A_m2": 46347760.28
      },
      {
        "H": 807.103,
        "A_m2": 48049800.11
      },
      {
        "H": 809.241,
        "A_m2": 48890361.1
      },
      {
        "H": 811.379,
        "A_m2": 49652066.97
      },
      {
        "H": 813.517,
        "A_m2": 50509762.93
      },
      {
        "H": 815.655,
        "A_m2": 51329584.96
      },
      {
        "H": 817.793,
        "A_m2": 52202533.33
      },
      {
        "H": 819.931,
        "A_m2": 53099002.48
      },
      {
        "H": 822.069,
        "A_m2": 54089702.82
      },
      {
        "H": 824.207,
        "A_m2": 54773669.99
      },
      {
        "H": 826.345,
        "A_m2": 55442131.86
      },
      {
        "H": 828.483,
        "A_m2": 56180181.13
      },
      {
        "H": 830.621,
        "A_m2": 57274288.41
      },
      {
        "H": 832.759,
        "A_m2": 58059164.81
      },
      {
        "H": 834.897,
        "A_m2": 59686436.5
      },
      {
        "H": 837.034,
        "A_m2": 60638322.98
      },
      {
        "H": 839.172,
        "A_m2": 61730502.91
      },
      {
        "H": 841.31,
        "A_m2": 62944216.71
      },
      {
        "H": 843.448,
        "A_m2": 63755440.32
      },
      {
        "H": 845.586,
        "A_m2": 64315890.11
      },
      {
        "H": 847.724,
        "A_m2": 64984407.08
      },
      {
        "H": 849.862,
        "A_m2": 65501673.01
      },
      {
        "H": 852.0,
        "A_m2": 66780786.05
      }
    ]
  },
  "s4": {
    "name": "沙坪",
    "channel": "ztb-sp",
    "n_sections": 30,
    "curve": [
      {
        "H": 549.0,
        "A_m2": 1164393.18
      },
      {
        "H": 549.241,
        "A_m2": 1179319.95
      },
      {
        "H": 549.483,
        "A_m2": 1216192.31
      },
      {
        "H": 549.724,
        "A_m2": 1228461.27
      },
      {
        "H": 549.966,
        "A_m2": 1228461.27
      },
      {
        "H": 550.207,
        "A_m2": 1274140.06
      },
      {
        "H": 550.448,
        "A_m2": 1279894.93
      },
      {
        "H": 550.69,
        "A_m2": 1286656.17
      },
      {
        "H": 550.931,
        "A_m2": 1300454.17
      },
      {
        "H": 551.172,
        "A_m2": 1325115.23
      },
      {
        "H": 551.414,
        "A_m2": 1366729.04
      },
      {
        "H": 551.655,
        "A_m2": 1378767.96
      },
      {
        "H": 551.897,
        "A_m2": 1393260.45
      },
      {
        "H": 552.138,
        "A_m2": 1427859.83
      },
      {
        "H": 552.379,
        "A_m2": 1444035.41
      },
      {
        "H": 552.621,
        "A_m2": 1458497.66
      },
      {
        "H": 552.862,
        "A_m2": 1467037.84
      },
      {
        "H": 553.103,
        "A_m2": 1487248.82
      },
      {
        "H": 553.345,
        "A_m2": 1511584.61
      },
      {
        "H": 553.586,
        "A_m2": 1525164.58
      },
      {
        "H": 553.828,
        "A_m2": 1546532.74
      },
      {
        "H": 554.069,
        "A_m2": 1551332.49
      },
      {
        "H": 554.31,
        "A_m2": 1568477.36
      },
      {
        "H": 554.552,
        "A_m2": 1573306.82
      },
      {
        "H": 554.793,
        "A_m2": 1582647.92
      },
      {
        "H": 555.034,
        "A_m2": 1582647.92
      },
      {
        "H": 555.276,
        "A_m2": 1594686.84
      },
      {
        "H": 555.517,
        "A_m2": 1600188.1
      },
      {
        "H": 555.759,
        "A_m2": 1600188.1
      },
      {
        "H": 556.0,
        "A_m2": 1655217.64
      }
    ]
  }
}